README.rst
setup.py
python_plus/LICENSE
python_plus/__init__.py
python_plus/__main__.py
python_plus/vem.man
python_plus.egg-info/PKG-INFO
python_plus.egg-info/SOURCES.txt
python_plus.egg-info/dependency_links.txt
python_plus.egg-info/entry_points.txt
python_plus.egg-info/not-zip-safe
python_plus.egg-info/requires.txt
python_plus.egg-info/top_level.txt
python_plus/docs/MAINPAGE.rst
python_plus/docs/Makefile
python_plus/docs/conf.py
python_plus/docs/index.rst
python_plus/docs/logozero_180x46.png
python_plus/docs/readthedocs.yml
python_plus/docs/requirements.txt
python_plus/docs/rtd_automodule.rst
python_plus/docs/rtd_changelog.rst
python_plus/docs/rtd_credits.rst
python_plus/docs/rtd_description.rst
python_plus/docs/rtd_getting_started.rst
python_plus/docs/rtd_usage.rst
python_plus/docs/rtd_usage_code_example.rst
python_plus/docs/rtd_usage_code_reference.rst
python_plus/docs/rtd_usage_vem.rst
python_plus/docs/_build/doctrees/environment.pickle
python_plus/docs/_build/doctrees/index.doctree
python_plus/docs/_build/doctrees/rtd_automodule.doctree
python_plus/docs/_build/doctrees/rtd_description.doctree
python_plus/docs/_build/doctrees/rtd_usage.doctree
python_plus/docs/_build/html/.buildinfo
python_plus/docs/_build/html/.nojekyll
python_plus/docs/_build/html/genindex.html
python_plus/docs/_build/html/index.html
python_plus/docs/_build/html/objects.inv
python_plus/docs/_build/html/py-modindex.html
python_plus/docs/_build/html/rtd_automodule.html
python_plus/docs/_build/html/rtd_description.html
python_plus/docs/_build/html/rtd_usage.html
python_plus/docs/_build/html/search.html
python_plus/docs/_build/html/searchindex.js
python_plus/docs/_build/html/_sources/index.rst.txt
python_plus/docs/_build/html/_sources/rtd_automodule.rst.txt
python_plus/docs/_build/html/_sources/rtd_description.rst.txt
python_plus/docs/_build/html/_sources/rtd_usage.rst.txt
python_plus/docs/_build/html/_static/_sphinx_javascript_frameworks_compat.js
python_plus/docs/_build/html/_static/basic.css
python_plus/docs/_build/html/_static/doctools.js
python_plus/docs/_build/html/_static/documentation_options.js
python_plus/docs/_build/html/_static/file.png
python_plus/docs/_build/html/_static/jquery-3.6.0.js
python_plus/egg-info/CHANGELOG.rst
python_plus/egg-info/CONTRIBUTORS.txt
python_plus/egg-info/DESCRIPTION.rst
python_plus/egg-info/README.txt
python_plus/egg-info/USAGE.rst
python_plus/egg-info/python_plus.rst
python_plus/egg-info/usage_code_example.rst
python_plus/egg-info/usage_code_reference.rst
python_plus/egg-info/usage_vem.rst
